langchain_llama_stack/__init__.py
langchain_llama_stack/_utils.py
langchain_llama_stack/chat_models.py
langchain_llama_stack/py.typed
langchain_llama_stack-0.1.0.dist-info/LICENSE
langchain_llama_stack-0.1.0.dist-info/METADATA
langchain_llama_stack-0.1.0.dist-info/WHEEL
langchain_llama_stack-0.1.0.dist-info/RECORD
