Metadata-Version: 2.1
Name: langchain-llama-stack
Version: 0.1.0
Summary: An integration package connecting LlamaStack and LangChain
Home-page: https://github.com/langchain-ai/langchain
License: MIT
Requires-Python: >=3.9,<4.0
Classifier: License :: OSI Approved :: MIT License
Classifier: Programming Language :: Python :: 3
Classifier: Programming Language :: Python :: 3.9
Classifier: Programming Language :: Python :: 3.10
Classifier: Programming Language :: Python :: 3.11
Classifier: Programming Language :: Python :: 3.12
Requires-Dist: langchain-core (>=0.3.47,<0.4.0)
Requires-Dist: llama-stack-client (>=0.1.8,<0.2.0)
Project-URL: Repository, https://github.com/langchain-ai/langchain
Project-URL: Release Notes, https://github.com/mattf/langchain-llama-stack/releases
Project-URL: Source Code, https://github.com/mattf/langchain-llama-stack
